fds/__init__.py
fds/sdk/__init__.py
fds/sdk/RealTimeOptions/__init__.py
fds/sdk/RealTimeOptions/api_client.py
fds/sdk/RealTimeOptions/configuration.py
fds/sdk/RealTimeOptions/exceptions.py
fds/sdk/RealTimeOptions/model_utils.py
fds/sdk/RealTimeOptions/rest.py
fds/sdk/RealTimeOptions/api/__init__.py
fds/sdk/RealTimeOptions/api/option_api.py
fds/sdk/RealTimeOptions/apis/__init__.py
fds/sdk/RealTimeOptions/model/__init__.py
fds/sdk/RealTimeOptions/model/attributes_member.py
fds/sdk/RealTimeOptions/model/get_option_get_data_type_items.py
fds/sdk/RealTimeOptions/model/inline_response200.py
fds/sdk/RealTimeOptions/model/inline_response2001.py
fds/sdk/RealTimeOptions/model/inline_response2001_meta.py
fds/sdk/RealTimeOptions/model/inline_response2002.py
fds/sdk/RealTimeOptions/model/inline_response2003.py
fds/sdk/RealTimeOptions/model/inline_response2004.py
fds/sdk/RealTimeOptions/model/inline_response2004_data.py
fds/sdk/RealTimeOptions/model/inline_response2004_data_currency.py
fds/sdk/RealTimeOptions/model/inline_response2004_data_prices.py
fds/sdk/RealTimeOptions/model/inline_response2004_data_prices_ask.py
fds/sdk/RealTimeOptions/model/inline_response200_data.py
fds/sdk/RealTimeOptions/model/inline_response200_data_class.py
fds/sdk/RealTimeOptions/model/inline_response200_data_exercise.py
fds/sdk/RealTimeOptions/model/inline_response200_data_life_cycle.py
fds/sdk/RealTimeOptions/model/inline_response200_data_life_cycle_delivery.py
fds/sdk/RealTimeOptions/model/inline_response200_data_life_cycle_expiration.py
fds/sdk/RealTimeOptions/model/inline_response200_data_life_cycle_maturity.py
fds/sdk/RealTimeOptions/model/inline_response200_data_market.py
fds/sdk/RealTimeOptions/model/inline_response200_data_open_interest.py
fds/sdk/RealTimeOptions/model/inline_response200_data_settlement.py
fds/sdk/RealTimeOptions/model/inline_response200_data_settlement_currency.py
fds/sdk/RealTimeOptions/model/inline_response200_data_strike_price.py
fds_sdk_realtimeoptions-0.1.0.dist-info/licenses/LICENSE
fds_sdk_realtimeoptions-0.1.0.dist-info/METADATA
fds_sdk_realtimeoptions-0.1.0.dist-info/WHEEL
fds_sdk_realtimeoptions-0.1.0.dist-info/top_level.txt
fds_sdk_realtimeoptions-0.1.0.dist-info/RECORD
